rags/__init__.py
rags-0.1.0.dist-info/METADATA
rags-0.1.0.dist-info/WHEEL
rags-0.1.0.dist-info/RECORD
